graceful/__init__.py
graceful/cookie.py
graceful/graceful.py
graceful/request.py
graceful/response.py
graceful/template.py
graceful/middleware/__init__.py
graceful/middleware/staticfiles.py
graceful_web-1.0.1.dist-info/LICENSE
graceful_web-1.0.1.dist-info/METADATA
graceful_web-1.0.1.dist-info/WHEEL
graceful_web-1.0.1.dist-info/top_level.txt
graceful_web-1.0.1.dist-info/RECORD
