Metadata-Version: 2.1
Name: graceful-web
Version: 1.0.1
Summary: A lightweight and efficient web framework
Home-page: https://github.com/nolanM123/graceful
Author: Nolan M. McAllister
Author-email: nolan.m.mcallister@gmail.com
License: MIT
Requires-Python: >=3.4
License-File: LICENSE
